README.md
setup.py
ssh_key_maker/__init__.py
ssh_key_maker/ssh_key_maker_bot.py
ssh_key_maker.egg-info/PKG-INFO
ssh_key_maker.egg-info/SOURCES.txt
ssh_key_maker.egg-info/dependency_links.txt
ssh_key_maker.egg-info/top_level.txt