Metadata-Version: 2.1
Name: ssh-key-maker
Version: 0.1.9
Summary: Package to generate SSH keys for windows users.
Home-page: UNKNOWN
Author: Pranav Chandran
Author-email: pranav.chandran@gmail.com
License: UNKNOWN
Platform: UNKNOWN
Classifier: Programming Language :: Python :: 3.9
Classifier: License :: OSI Approved :: MIT License
Classifier: Operating System :: OS Independent
